djazz/__init__.py
djazz/asgi.py
djazz/settings.py
djazz/urls.py
djazz/wsgi.py
django_djazz-0.1.0rc1.dist-info/LICENSE
django_djazz-0.1.0rc1.dist-info/WHEEL
django_djazz-0.1.0rc1.dist-info/METADATA
django_djazz-0.1.0rc1.dist-info/RECORD
