Metadata-Version: 2.1
Name: django-djazz
Version: 0.1.0rc1
Summary: A ready-to-use Django project tailored for practical, real-world applications, djazz comes with pre-configured essential settings and industry best practices built-in, ensuring a streamlined development process right out of the box. Ideal for developers looking to jumpstart their projects without the hassle of initial setup.
Author-email: Azat <to@azat.cc>
Project-URL: Home, https://github.com/azataiot/djazz 
Project-URL: Source, https://github.com/azataiot/djazz 
